{
    "frame": "102",
    "image_filename": "render_102.png",
    "image_resolution": {
        "width": 1920,
        "height": 1080
    },
    "camera_parameters": {
        "intrinsic_matrix": [
            [
                2666.666666666667,
                0,
                960.0
            ],
            [
                0,
                2250.0,
                540.0
            ],
            [
                0,
                0,
                1
            ]
        ],
        "extrinsic_matrix": [
            [
                0.3728128969669342,
                -0.9279065728187561,
                8.568168397005138e-08,
                -2.384716992764879e-07
            ],
            [
                -0.02193175069987774,
                -0.00881163589656353,
                0.9997206926345825,
                -3.071535843446327e-07
            ],
            [
                -0.9276473522186279,
                -0.3727087676525116,
                -0.02363572083413601,
                -11.256316184997559
            ],
            [
                -0.0,
                0.0,
                -0.0,
                1.0
            ]
        ],
        "camera_location": [
            -10.44189167022705,
            -4.1953277587890625,
            -0.26605066657066345
        ],
        "camera_rotation_euler": [
            1.1093189716339111,
            0.0,
            0.8149281740188599
        ],
        "camera_rotation_quaternion": [
            0.5788707733154297,
            0.5927183628082275,
            -0.400628000497818,
            -0.39126813411712646
        ],
        "focal_length": 50.0,
        "sensor_width": 36.0,
        "sensor_height": 24.0
    },
    "objects": [
        {
            "object_name": "Cube",
            "bbox_2d": {
                "x_min": 665.7434172795606,
                "y_min": 320.49451689984926,
                "x_max": 1284.842646187747,
                "y_max": 772.3283979725478,
                "width": 619.0992289081864,
                "height": 451.83388107269855,
                "center_x": 975.2930317336538,
                "center_y": 546.4114574361986
            },
            "visible_vertices": 8,
            "total_vertices": 8
        }
    ],
    "metadata": {
        "total_objects": 1,
        "render_settings": {
            "resolution_percentage": 50,
            "file_format": "PNG"
        }
    }
}