{
    "frame": "886",
    "image_filename": "render_886.png",
    "image_resolution": {
        "width": 1920,
        "height": 1080
    },
    "camera_parameters": {
        "intrinsic_matrix": [
            [
                2666.666666666667,
                0,
                960.0
            ],
            [
                0,
                2250.0,
                540.0
            ],
            [
                0,
                0,
                1
            ]
        ],
        "extrinsic_matrix": [
            [
                -0.9976579546928406,
                0.06840039044618607,
                -9.033828973770142e-08,
                -1.1929762422369095e-07
            ],
            [
                0.00408979644998908,
                0.05965329334139824,
                0.9982107877731323,
                -8.360780725524819e-07
            ],
            [
                0.06827801465988159,
                0.9958729147911072,
                -0.059793319553136826,
                -11.256316184997559
            ],
            [
                -0.0,
                0.0,
                0.0,
                1.0
            ]
        ],
        "camera_location": [
            0.7685588598251343,
            11.209860801696777,
            -0.6730517745018005
        ],
        "camera_rotation_euler": [
            1.1093189716339111,
            0.0,
            0.8149281740188599
        ],
        "camera_rotation_quaternion": [
            0.023462824523448944,
            0.024910248816013336,
            0.7275136709213257,
            0.6852392554283142
        ],
        "focal_length": 50.0,
        "sensor_width": 36.0,
        "sensor_height": 24.0
    },
    "objects": [
        {
            "object_name": "Cube",
            "bbox_2d": {
                "x_min": 683.1627105790243,
                "y_min": 332.4914163520341,
                "x_max": 1204.5646700541631,
                "y_max": 773.0671082621905,
                "width": 521.4019594751388,
                "height": 440.57569191015637,
                "center_x": 943.8636903165936,
                "center_y": 552.7792623071123
            },
            "visible_vertices": 8,
            "total_vertices": 8
        }
    ],
    "metadata": {
        "total_objects": 1,
        "render_settings": {
            "resolution_percentage": 50,
            "file_format": "PNG"
        }
    }
}