{
    "frame": "636",
    "image_filename": "render_636.png",
    "image_resolution": {
        "width": 1920,
        "height": 1080
    },
    "camera_parameters": {
        "intrinsic_matrix": [
            [
                2666.666666666667,
                0,
                960.0
            ],
            [
                0,
                2250.0,
                540.0
            ],
            [
                0,
                0,
                1
            ]
        ],
        "extrinsic_matrix": [
            [
                0.6215667724609375,
                -0.7833612561225891,
                0.0,
                4.775493493980321e-07
            ],
            [
                -0.058765143156051636,
                -0.04662782698869705,
                0.9971823692321777,
                -1.3043221258612903e-07
            ],
            [
                -0.7811539173126221,
                -0.6198154091835022,
                -0.07501663267612457,
                -11.256316184997559
            ],
            [
                -0.0,
                0.0,
                -0.0,
                1.0
            ]
        ],
        "camera_location": [
            -8.792915344238281,
            -6.976837635040283,
            -0.8444108366966248
        ],
        "camera_rotation_euler": [
            1.1093189716339111,
            0.0,
            0.8149281740188599
        ],
        "camera_rotation_quaternion": [
            0.6123566031455994,
            0.6601536273956299,
            -0.3189130127429962,
            -0.29582276940345764
        ],
        "focal_length": 50.0,
        "sensor_width": 36.0,
        "sensor_height": 24.0
    },
    "objects": [
        {
            "object_name": "Cube",
            "bbox_2d": {
                "x_min": 629.6997498994839,
                "y_min": 334.84062756571643,
                "x_max": 1299.9715471741156,
                "y_max": 789.8190648120413,
                "width": 670.2717972746317,
                "height": 454.9784372463249,
                "center_x": 964.8356485367997,
                "center_y": 562.329846188879
            },
            "visible_vertices": 8,
            "total_vertices": 8
        }
    ],
    "metadata": {
        "total_objects": 1,
        "render_settings": {
            "resolution_percentage": 50,
            "file_format": "PNG"
        }
    }
}