{
    "frame": "403",
    "image_filename": "render_403.png",
    "image_resolution": {
        "width": 1920,
        "height": 1080
    },
    "camera_parameters": {
        "intrinsic_matrix": [
            [
                2666.666666666667,
                0,
                960.0
            ],
            [
                0,
                2250.0,
                540.0
            ],
            [
                0,
                0,
                1
            ]
        ],
        "extrinsic_matrix": [
            [
                0.2341805249452591,
                -0.97219318151474,
                3.678724880273876e-08,
                2.3847618990657793e-07
            ],
            [
                0.018521679565310478,
                0.004461470525711775,
                0.9998185634613037,
                1.4854803112029913e-06
            ],
            [
                -0.9720167517662048,
                -0.23413807153701782,
                0.019051404669880867,
                -11.256316184997559
            ],
            [
                -0.0,
                0.0,
                -0.0,
                1.0
            ]
        ],
        "camera_location": [
            -10.941327095031738,
            -2.635531187057495,
            0.2144475132226944
        ],
        "camera_rotation_euler": [
            1.1093189716339111,
            0.0,
            0.8149281740188599
        ],
        "camera_rotation_quaternion": [
            0.5607346892356873,
            0.5501517653465271,
            -0.4333675503730774,
            -0.4417039752006531
        ],
        "focal_length": 50.0,
        "sensor_width": 36.0,
        "sensor_height": 24.0
    },
    "objects": [
        {
            "object_name": "Cube",
            "bbox_2d": {
                "x_min": 691.3604496924706,
                "y_min": 311.45180205969973,
                "x_max": 1266.3984813952388,
                "y_max": 759.10667026608,
                "width": 575.0380317027682,
                "height": 447.65486820638023,
                "center_x": 978.8794655438547,
                "center_y": 535.2792361628899
            },
            "visible_vertices": 8,
            "total_vertices": 8
        }
    ],
    "metadata": {
        "total_objects": 1,
        "render_settings": {
            "resolution_percentage": 50,
            "file_format": "PNG"
        }
    }
}