{
    "frame": "103",
    "image_filename": "render_103.png",
    "image_resolution": {
        "width": 1920,
        "height": 1080
    },
    "camera_parameters": {
        "intrinsic_matrix": [
            [
                2666.666666666667,
                0,
                960.0
            ],
            [
                0,
                2250.0,
                540.0
            ],
            [
                0,
                0,
                1
            ]
        ],
        "extrinsic_matrix": [
            [
                -0.717555582523346,
                0.6965010166168213,
                2.3096791323951038e-07,
                -4.7682675585747347e-07
            ],
            [
                -0.022913198918104172,
                -0.02360609918832779,
                0.9994586706161499,
                -5.057059979662881e-07
            ],
            [
                0.6961240172386169,
                0.717167317867279,
                0.03289790078997612,
                -11.256315231323242
            ],
            [
                -0.0,
                0.0,
                -0.0,
                1.0
            ]
        ],
        "camera_location": [
            7.8357930183410645,
            8.072662353515625,
            0.37030813097953796
        ],
        "camera_rotation_euler": [
            1.1093189716339111,
            0.0,
            0.8149281740188599
        ],
        "camera_rotation_quaternion": [
            0.27006295323371887,
            0.261320024728775,
            0.6444090008735657,
            0.66596919298172
        ],
        "focal_length": 50.0,
        "sensor_width": 36.0,
        "sensor_height": 24.0
    },
    "objects": [
        {
            "object_name": "Cube",
            "bbox_2d": {
                "x_min": 623.3912911043344,
                "y_min": 301.69805591727413,
                "x_max": 1295.348966256263,
                "y_max": 758.5611435044582,
                "width": 671.9576751519287,
                "height": 456.86308758718405,
                "center_x": 959.3701286802988,
                "center_y": 530.1295997108662
            },
            "visible_vertices": 8,
            "total_vertices": 8
        }
    ],
    "metadata": {
        "total_objects": 1,
        "render_settings": {
            "resolution_percentage": 50,
            "file_format": "PNG"
        }
    }
}