{
    "frame": "360",
    "image_filename": "render_360.png",
    "image_resolution": {
        "width": 1920,
        "height": 1080
    },
    "camera_parameters": {
        "intrinsic_matrix": [
            [
                2666.666666666667,
                0,
                960.0
            ],
            [
                0,
                2250.0,
                540.0
            ],
            [
                0,
                0,
                1
            ]
        ],
        "extrinsic_matrix": [
            [
                0.8447155952453613,
                -0.5352153778076172,
                2.60770320892334e-08,
                -1.430293764315138e-06
            ],
            [
                0.045824818313121796,
                0.07232407480478287,
                0.9963278770446777,
                3.155475383209705e-07
            ],
            [
                -0.533250093460083,
                -0.84161376953125,
                0.08561941981315613,
                -11.256316184997559
            ],
            [
                -0.0,
                0.0,
                -0.0,
                1.0
            ]
        ],
        "camera_location": [
            -6.002429962158203,
            -9.473470687866211,
            0.9637589454650879
        ],
        "camera_rotation_euler": [
            1.1093189716339111,
            0.0,
            0.8149281740188599
        ],
        "camera_rotation_quaternion": [
            0.7075766921043396,
            0.6493789553642273,
            -0.18840716779232025,
            -0.20529231429100037
        ],
        "focal_length": 50.0,
        "sensor_width": 36.0,
        "sensor_height": 24.0
    },
    "objects": [
        {
            "object_name": "Cube",
            "bbox_2d": {
                "x_min": 621.2318907381358,
                "y_min": 288.4143675597288,
                "x_max": 1280.5680332160612,
                "y_max": 741.7085760112153,
                "width": 659.3361424779254,
                "height": 453.2942084514865,
                "center_x": 950.8999619770984,
                "center_y": 515.0614717854721
            },
            "visible_vertices": 8,
            "total_vertices": 8
        }
    ],
    "metadata": {
        "total_objects": 1,
        "render_settings": {
            "resolution_percentage": 50,
            "file_format": "PNG"
        }
    }
}