{
    "frame": "107",
    "image_filename": "render_107.png",
    "image_resolution": {
        "width": 1920,
        "height": 1080
    },
    "camera_parameters": {
        "intrinsic_matrix": [
            [
                2666.666666666667,
                0,
                960.0
            ],
            [
                0,
                2250.0,
                540.0
            ],
            [
                0,
                0,
                1
            ]
        ],
        "extrinsic_matrix": [
            [
                0.6473421454429626,
                0.7621995210647583,
                -4.284083843231201e-08,
                0.05869141221046448
            ],
            [
                0.0343027338385582,
                -0.029133491218090057,
                0.9989868402481079,
                -1.0788418054580688
            ],
            [
                0.7614272832870483,
                -0.6466862559318542,
                -0.04500485211610794,
                -11.338808059692383
            ],
            [
                -0.0,
                0.0,
                -0.0,
                1.0
            ]
        ],
        "camera_location": [
            8.632691383361816,
            -7.408816337585449,
            0.5674471259117126
        ],
        "camera_rotation_euler": [
            1.1093189716339111,
            0.0,
            0.8149281740188599
        ],
        "camera_rotation_quaternion": [
            0.6271371245384216,
            0.6560260057449341,
            0.30353304743766785,
            0.29016655683517456
        ],
        "focal_length": 50.0,
        "sensor_width": 36.0,
        "sensor_height": 24.0
    },
    "objects": [
        {
            "object_name": "Cube",
            "bbox_2d": {
                "x_min": 492.0014762878418,
                "y_min": 26.07532024383545,
                "x_max": 1419.8355102539062,
                "y_max": 950.3946599364281,
                "width": 927.8340339660645,
                "height": 924.3193396925926,
                "center_x": 955.918493270874,
                "center_y": 488.23499009013176
            },
            "visible_vertices": 8,
            "total_vertices": 8
        }
    ],
    "metadata": {
        "total_objects": 1,
        "render_settings": {
            "resolution_percentage": 50,
            "file_format": "PNG"
        }
    }
}