{
    "frame": "36",
    "image_filename": "render_036.png",
    "image_resolution": {
        "width": 1920,
        "height": 1080
    },
    "camera_parameters": {
        "intrinsic_matrix": [
            [
                2666.666666666667,
                0,
                960.0
            ],
            [
                0,
                2250.0,
                540.0
            ],
            [
                0,
                0,
                1
            ]
        ],
        "extrinsic_matrix": [
            [
                -0.09717877209186554,
                -0.9952669143676758,
                -1.5320256352424622e-07,
                0.02466076798737049
            ],
            [
                -0.04505923017859459,
                0.004399479366838932,
                0.9989746809005737,
                -1.0908498764038086
            ],
            [
                -0.9942464232444763,
                0.09707915037870407,
                -0.045273493975400925,
                -11.604509353637695
            ],
            [
                -0.0,
                0.0,
                -0.0,
                1.0
            ]
        ],
        "camera_location": [
            -11.584498405456543,
            1.155898928642273,
            0.5643544793128967
        ],
        "camera_rotation_euler": [
            1.1093189716339111,
            0.0,
            0.8149281740188599
        ],
        "camera_rotation_quaternion": [
            0.4642055630683899,
            0.4857198894023895,
            -0.5354558229446411,
            -0.511738657951355
        ],
        "focal_length": 50.0,
        "sensor_width": 36.0,
        "sensor_height": 24.0
    },
    "objects": [
        {
            "object_name": "Cube",
            "bbox_2d": {
                "x_min": 534.2133522033691,
                "y_min": 155.5633807182312,
                "x_max": 1432.1207427978516,
                "y_max": 1025.0587691366673,
                "width": 897.9073905944824,
                "height": 869.495388418436,
                "center_x": 983.1670475006104,
                "center_y": 590.3110749274492
            },
            "visible_vertices": 8,
            "total_vertices": 8
        }
    ],
    "metadata": {
        "total_objects": 1,
        "render_settings": {
            "resolution_percentage": 50,
            "file_format": "PNG"
        }
    }
}