{
    "frame": "414",
    "image_filename": "render_414.png",
    "image_resolution": {
        "width": 1920,
        "height": 1080
    },
    "camera_parameters": {
        "intrinsic_matrix": [
            [
                2666.666666666667,
                0,
                960.0
            ],
            [
                0,
                2250.0,
                540.0
            ],
            [
                0,
                0,
                1
            ]
        ],
        "extrinsic_matrix": [
            [
                -0.7275407910346985,
                0.6860643625259399,
                2.2351740014414645e-08,
                -0.12458618730306625
            ],
            [
                -0.13295437395572662,
                -0.1409921795129776,
                0.9810425043106079,
                -1.0777579545974731
            ],
            [
                0.673058271408081,
                0.7137485146522522,
                0.1937929391860962,
                -11.661730766296387
            ],
            [
                -0.0,
                -0.0,
                -0.0,
                1.0
            ]
        ],
        "camera_location": [
            7.615090370178223,
            8.257060050964355,
            3.3172860145568848
        ],
        "camera_rotation_euler": [
            1.1093189716339111,
            0.0,
            0.8149281740188599
        ],
        "camera_rotation_quaternion": [
            0.2851577699184418,
            0.2343386858701706,
            0.5900753140449524,
            0.7180399894714355
        ],
        "focal_length": 50.0,
        "sensor_width": 36.0,
        "sensor_height": 24.0
    },
    "objects": [
        {
            "object_name": "Cube",
            "bbox_2d": {
                "x_min": 431.7575740814209,
                "y_min": 93.4503722190857,
                "x_max": 1467.9446411132812,
                "y_max": 996.3600191473961,
                "width": 1036.1870670318604,
                "height": 902.9096469283104,
                "center_x": 949.8511075973511,
                "center_y": 544.9051956832409
            },
            "visible_vertices": 8,
            "total_vertices": 8
        }
    ],
    "metadata": {
        "total_objects": 1,
        "render_settings": {
            "resolution_percentage": 50,
            "file_format": "PNG"
        }
    }
}