{
    "frame": "315",
    "image_filename": "render_315.png",
    "image_resolution": {
        "width": 1920,
        "height": 1080
    },
    "camera_parameters": {
        "intrinsic_matrix": [
            [
                2666.666666666667,
                0,
                960.0
            ],
            [
                0,
                2250.0,
                540.0
            ],
            [
                0,
                0,
                1
            ]
        ],
        "extrinsic_matrix": [
            [
                0.8513274192810059,
                0.524634838104248,
                -7.450580596923828e-09,
                0.09534117579460144
            ],
            [
                -0.027201220393180847,
                0.044139571487903595,
                0.9986549615859985,
                -1.0895962715148926
            ],
            [
                0.523929238319397,
                -0.8501823544502258,
                0.05184793472290039,
                -11.46838665008545
            ],
            [
                -0.0,
                0.0,
                -0.0,
                1.0
            ]
        ],
        "camera_location": [
            5.897817611694336,
            -9.752144813537598,
            1.6827428340911865
        ],
        "camera_rotation_euler": [
            1.1093189716339111,
            0.0,
            0.8149281740188599
        ],
        "camera_rotation_quaternion": [
            0.6977311372756958,
            0.6624462008476257,
            0.18772603571414948,
            0.19772517681121826
        ],
        "focal_length": 50.0,
        "sensor_width": 36.0,
        "sensor_height": 24.0
    },
    "objects": [
        {
            "object_name": "Cube",
            "bbox_2d": {
                "x_min": 499.19042587280273,
                "y_min": 56.694345474243164,
                "x_max": 1385.1100158691406,
                "y_max": 922.2725754976273,
                "width": 885.9195899963379,
                "height": 865.5782300233841,
                "center_x": 942.1502208709717,
                "center_y": 489.4834604859352
            },
            "visible_vertices": 8,
            "total_vertices": 8
        }
    ],
    "metadata": {
        "total_objects": 1,
        "render_settings": {
            "resolution_percentage": 50,
            "file_format": "PNG"
        }
    }
}