{
    "frame": "391",
    "image_filename": "render_391.png",
    "image_resolution": {
        "width": 1920,
        "height": 1080
    },
    "camera_parameters": {
        "intrinsic_matrix": [
            [
                2666.666666666667,
                0,
                960.0
            ],
            [
                0,
                2250.0,
                540.0
            ],
            [
                0,
                0,
                1
            ]
        ],
        "extrinsic_matrix": [
            [
                0.5353012084960938,
                0.8446611762046814,
                0.0,
                0.040388088673353195
            ],
            [
                -0.2658310830593109,
                0.1684696525335312,
                0.9491846561431885,
                -1.0729215145111084
            ],
            [
                0.8017395734786987,
                -0.5080996751785278,
                0.3147192895412445,
                -11.729164123535156
            ],
            [
                -0.0,
                0.0,
                -0.0,
                1.0
            ]
        ],
        "camera_location": [
            9.096900939941406,
            -5.812946796417236,
            4.7097954750061035
        ],
        "camera_rotation_euler": [
            1.1093189716339111,
            0.0,
            0.8149281740188599
        ],
        "camera_rotation_quaternion": [
            0.7103679776191711,
            0.5128626227378845,
            0.28215649724006653,
            0.39081594347953796
        ],
        "focal_length": 50.0,
        "sensor_width": 36.0,
        "sensor_height": 24.0
    },
    "objects": [
        {
            "object_name": "Cube",
            "bbox_2d": {
                "x_min": 504.9928092956543,
                "y_min": 157.64378786087036,
                "x_max": 1416.7523574829102,
                "y_max": 916.7278701066971,
                "width": 911.7595481872559,
                "height": 759.0840822458267,
                "center_x": 960.8725833892822,
                "center_y": 537.1858289837837
            },
            "visible_vertices": 8,
            "total_vertices": 8
        }
    ],
    "metadata": {
        "total_objects": 1,
        "render_settings": {
            "resolution_percentage": 50,
            "file_format": "PNG"
        }
    }
}