{
    "frame": "333",
    "image_filename": "render_333.png",
    "image_resolution": {
        "width": 1920,
        "height": 1080
    },
    "camera_parameters": {
        "intrinsic_matrix": [
            [
                2666.666666666667,
                0,
                960.0
            ],
            [
                0,
                2250.0,
                540.0
            ],
            [
                0,
                0,
                1
            ]
        ],
        "extrinsic_matrix": [
            [
                0.11176667362451553,
                -0.9937344193458557,
                -6.332992796842518e-08,
                0.05289476737380028
            ],
            [
                -0.14172814786434174,
                -0.01594041846692562,
                0.989777147769928,
                -1.0931801795959473
            ],
            [
                -0.983575701713562,
                -0.11062410473823547,
                -0.1426217406988144,
                -11.489481925964355
            ],
            [
                -0.0,
                0.0,
                -0.0,
                1.0
            ]
        ],
        "camera_location": [
            -11.461623191833496,
            -1.235876202583313,
            -0.5566450953483582
        ],
        "camera_rotation_euler": [
            1.1093189716339111,
            0.0,
            0.8149281740188599
        ],
        "camera_rotation_quaternion": [
            0.48816096782684326,
            0.5635443329811096,
            -0.5037148594856262,
            -0.4363347291946411
        ],
        "focal_length": 50.0,
        "sensor_width": 36.0,
        "sensor_height": 24.0
    },
    "objects": [
        {
            "object_name": "Cube",
            "bbox_2d": {
                "x_min": 563.8153839111328,
                "y_min": 134.63075637817383,
                "x_max": 1415.4702758789062,
                "y_max": 995.3847196698189,
                "width": 851.6548919677734,
                "height": 860.753963291645,
                "center_x": 989.6428298950195,
                "center_y": 565.0077380239964
            },
            "visible_vertices": 8,
            "total_vertices": 8
        }
    ],
    "metadata": {
        "total_objects": 1,
        "render_settings": {
            "resolution_percentage": 50,
            "file_format": "PNG"
        }
    }
}